isfloattool/__init__.py
isfloattool/__main__.py
isfloattool-0.1.0.dist-info/METADATA
isfloattool-0.1.0.dist-info/WHEEL
isfloattool-0.1.0.dist-info/entry_points.txt
isfloattool-0.1.0.dist-info/top_level.txt
isfloattool-0.1.0.dist-info/RECORD
