Metadata-Version: 2.4
Name: isfloattool
Version: 0.1.0
Summary: tool to check if input is float number
Requires-Python: >=3.8
